ppai/__init__.py
ppai/pp_ai.py
ppai/exceptions/__init__.py
ppai/exceptions/api_connection_error.py
ppai/exceptions/api_error.py
ppai/exceptions/api_status_error.py
ppai/exceptions/api_token_not_found_error.py
ppai/exceptions/authentication_error.py
ppai/exceptions/bad_request_error.py
ppai/exceptions/internal_server_error.py
ppai/exceptions/not_found_error.py
ppai/exceptions/permission_denied_error.py
ppai/exceptions/rate_limit_error.py
ppai/exceptions/unprocessable_entity_error.py
ppai/resources/__init__.py
ppai/resources/chat.py
ppai/resources/completions.py
ppai/resources/models.py
ppai/types/__init__.py
ppai/types/api_token_valid.py
ppai/types/chat_completion.py
ppai/types/chat_completion_chunk.py
ppai/types/chat_completion_message.py
ppai/types/choice.py
ppai/types/choice_delta.py
ppai/types/completion_usage.py
ppai/types/model.py
ppai/types/model_list.py
ppai/types/stream.py
ppai/types/stream_choice.py
ppai/utils/__init__.py
ppai/utils/http_client.py
ppai/validators/__init__.py
ppai/validators/api_token_validator.py
ppai_dev-0.1.2.dist-info/LICENSE
ppai_dev-0.1.2.dist-info/METADATA
ppai_dev-0.1.2.dist-info/WHEEL
ppai_dev-0.1.2.dist-info/top_level.txt
ppai_dev-0.1.2.dist-info/RECORD
