Metadata-Version: 2.1
Name: ppai-dev
Version: 0.1.2
Summary: The official PeakPrivacy library for the ai API
Home-page: https://github.com/freihandlabor/peakprivacyai-python-dev
Author: PeakPrivacy
Author-email: PeakPrivacy <support@pp.com>
License: MIT License
Project-URL: Homepage, https://api.peakprivacy.ch/
Project-URL: Repository, https://github.com/freihandlabor/peakprivacyai-python-dev?tab=MIT-1-ov-file
Project-URL: Documentation, https://peakprivacy.ch/en/guide/api
Project-URL: Issues, https://github.com/freihandlabor/peakprivacyai-python-dev/issues
Project-URL: Changelog, https://github.com/freihandlabor/peakprivacyai-python-dev/blob/main/CHANGELOG.md
Classifier: Development Status :: 4 - Beta
Classifier: Intended Audience :: Developers
Classifier: Topic :: Software Development :: Libraries :: Python Modules
Classifier: License :: OSI Approved :: MIT License
Classifier: Programming Language :: Python :: 3.7
Classifier: Programming Language :: Python :: 3.7
Classifier: Programming Language :: Python :: 3.8
Classifier: Programming Language :: Python :: 3.9
Classifier: Programming Language :: Python :: 3.10
Classifier: Programming Language :: Python :: 3.11
Classifier: Programming Language :: Python :: 3.12
Requires-Python: >=3.7.1
License-File: LICENSE
Requires-Dist: requests ==2.31.0
Requires-Dist: typing
